Metadata-Version: 1.0
Name: into
Version: 0.2.2
Summary: Data migration utilities
Home-page: http://github.com/ContinuumIO/into/
Author: Matthew Rocklin
Author-email: mrocklin@continuum.io
License: BSD
Keywords: into data conversion hdf5 sql blaze
Platform: UNKNOWN
